aiprog/__init__.py
aiprog/prg.py
aiprog-0.1.0.dist-info/METADATA
aiprog-0.1.0.dist-info/WHEEL
aiprog-0.1.0.dist-info/top_level.txt
aiprog-0.1.0.dist-info/RECORD
